sqlalchemy_equivalence
