Metadata-Version: 1.1
Name: SQLAlchemy-Equivalence
Version: 0.1.1
Summary: Provides natural equivalence support for SQLAlchemy declarative models.
Home-page: https://github.com/kvesteri/sqlalchemy-equivalence
Author: Konsta Vesterinen
Author-email: konsta@fastmonkeys.com
License: BSD
Platform: any
Classifier: Environment :: Web Environment
Classifier: Intended Audience :: Developers
Classifier: License :: OSI Approved :: BSD License
Classifier: Operating System :: OS Independent
Classifier: Programming Language :: Python
Classifier: Topic :: Internet :: WWW/HTTP :: Dynamic Content
Classifier: Topic :: Software Development :: Libraries :: Python Modules
